{"stats":{"minecraft:used":{"minecraft:stone_bricks":69,"minecraft:wooden_axe":1,"minecraft:torch":3,"minecraft:dirt_path":12,"minecraft:grass_block":170},"minecraft:custom":{"minecraft:jump":17,"minecraft:time_since_rest":20386,"minecraft:leave_game":1,"minecraft:damage_dealt":17,"minecraft:crouch_one_cm":8,"minecraft:sprint_one_cm":869,"minecraft:play_time":20386,"minecraft:time_since_death":20386,"minecraft:walk_one_cm":21283,"minecraft:sneak_time":163,"minecraft:total_world_time":26036,"minecraft:fly_one_cm":220102}},"DataVersion":3105}